DENO_DW/__init__.py
DENO_DOWNLOAD-0.2.0.dist-info/METADATA
DENO_DOWNLOAD-0.2.0.dist-info/WHEEL
DENO_DOWNLOAD-0.2.0.dist-info/top_level.txt
DENO_DOWNLOAD-0.2.0.dist-info/RECORD
