Metadata-Version: 2.1
Name: DENO_DOWNLOAD
Version: 0.2.0
Summary: Thư Viện Về API Download Media
Author: DENO
Author-email: vinhytb3010@gmail.com
Keywords: Facebook video download,Youtube video download,Tiktok video download,API video download,DENO_DOWNLOAD,DENO
Classifier: Programming Language :: Python :: 3
Classifier: License :: OSI Approved :: MIT License
Classifier: Operating System :: OS Independent
Requires-Dist: requests
Requires-Dist: clint
Requires-Dist: sockets
Requires-Dist: dnspython
